{
  "addressBook.contactAddress": "連絡先アドレス",
  "addressBook.contactName": "連絡先",
  "addressBook.typeContact": "保存された連絡先",
  "addressBook.typeRecent": "最近",
  "addressBook.typeWallet": "あなたのウォレット",
  "applyMasterPassword.accounts": " accounts",
  "applyMasterPassword.andOther": "他、",
  "applyMasterPassword.applyMasterPassword": "マスターパスワードを適用",
  "applyMasterPassword.applyMasterPasswordMessage": "マスターパスワードの作成に成功しました。マスターパスワードを既存のアカウントに適用してくださ",
  "attachAccount.attachAWatchOnlyAccount": "ウォッチのみのアカウントをアタッチ",
  "attachAccount.attachWatchOnlyAccMessage": "秘密鍵のないウォレットのアクティビティを追跡する",
  "attachAccount.connectAKeystoneDevice": "Keystone デバイスを接続",
  "attachAccount.connectALedgerDevice": "Ledger デバイスを接続",
  "attachAccount.connectAPolkadotVaultAcc": "Polkadot Vault アカウントを接続",
  "attachAccount.connectKeystoneMessage1": "Keystoneの \"Software Wallet \"セクションを開き、SubWalletを選択します。",
  "attachAccount.connectKeystoneMessage2": "Keystoneがスキャン用のQRコードを提供します。",
  "attachAccount.connectPolkadotVaultMessage1": "携帯電話でPolkadot Vaultを開き、ウォレットに接続します。",
  "attachAccount.connectPolkadotVaultMessage2": "Polkadot Vaultがスキャン用のQRコードを提供します。",
  "attachAccount.readThisInstructionForMoreDetailsP1": "詳しくは",
  "attachAccount.readThisInstructionForMoreDetailsP2": "こちら",
  "attachAccount.readThisInstructionForMoreDetailsP3": "の説明をお読みください。",
  "attachAccount.scanQrCode": "QRコードをスキャン",
  "browser.all": "すべて",
  "browser.clearHistory": "履歴をクリア",
  "browser.community": "コミュニティ",
  "browser.crowdloans": "クラウドローン",
  "browser.data": "データ",
  "browser.defi": "DeFi",
  "browser.EVM": "EVM",
  "browser.favorite": "お気に入り",
  "browser.missionPool": "Mission pool",
  "browser.nft": "NFT",
  "browser.recent": "最近",
  "browser.recommended": "推奨",
  "browser.searchWithDuckduckgo": "Duckduckgo で検索",
  "browser.seeAll": "すべてを見る",
  "browser.staking": "ステーキング",
  "browser.test": "テスト",
  "browser.utilities": "ユーティリティ",
  "buttonTitles.addContact": "連絡先を追加",
  "buttonTitles.addNetwork": "Add network",
  "buttonTitles.addNewProvider": "新しいプロバイダーを追加",
  "buttonTitles.addNft": "Add NFT",
  "buttonTitles.addToken": "Add token",
  "buttonTitles.agree": "Agree",
  "buttonTitles.apply": "申し込み",
  "buttonTitles.applyAccounts": "{0} アカウントを申請する",
  "buttonTitles.applyCollator": "{0} コレーター を適用する",
  "buttonTitles.applyCollators": "{0} コレーター を適用する",
  "buttonTitles.applyDApp": "{0} dApp を適用する",
  "buttonTitles.applyDApps": "{0} dApp を適用する",
  "buttonTitles.applyFilter": "フィルターを適用",
  "buttonTitles.applyMasterPassword": "今すぐマスターパスワードを適用してください",
  "buttonTitles.applyValidator": "{0} バリデータ ーを適用する",
  "buttonTitles.applyValidators": "{0} バリデータ ーを適用する",
  "buttonTitles.approve": "承認",
  "buttonTitles.attachWatchOnlyAcc": "ウォッチのみのアカウントをアタッチ",
  "buttonTitles.backToHome": "ホームに戻る",
  "buttonTitles.buyNow": "今すぐ購入",
  "buttonTitles.cancel": "キャンセル",
  "buttonTitles.cancelUnstake": "Cancel unstake",
  "buttonTitles.cancelUnstaking": "アンステーキングをキャンセル",
  "buttonTitles.claimRewards": "報酬を請求する",
  "buttonTitles.confirm": "確認",
  "buttonTitles.connectLedgerDevice": "Ledger デバイスを接続",
  "buttonTitles.continue": "続く",
  "buttonTitles.copyToClipboard": "クリップボードにコピー",
  "buttonTitles.createANewAcc": "新しいアカウントを作成",
  "buttonTitles.createMasterPassword": "マスターパスワードを作成",
  "buttonTitles.createOne": "一つ作る",
  "buttonTitles.creating": "作成",
  "buttonTitles.delete": "削除",
  "buttonTitles.deriveAnAcc": "派生アカウント",
  "buttonTitles.disconnect": "切断",
  "buttonTitles.doNotRememberYourPassword": "パスワードを覚えていませんか？",
  "buttonTitles.enable": "Enable",
  "buttonTitles.enableNetwork": "ネットワークを有効化",
  "buttonTitles.enterMasterPassword": "Enter master password",
  "buttonTitles.exploreEarningOptions": "Explore earning options",
  "buttonTitles.exportThisAcc": "このアカウントをエクスポート",
  "buttonTitles.finish": "終了",
  "buttonTitles.forgetThisAccount": "このアカウントを削除する",
  "buttonTitles.generalTermCheckbox": "私は、SubWallet とそのすべての機能の使用を規定する本契約の条件を理解し、これに同意します",
  "buttonTitles.iDontCare": "I don't care",
  "buttonTitles.import": "インポート",
  "buttonTitles.importAccount": "アカウントをインポート",
  "buttonTitles.importByJsonFile": "JSONファイルによるインポート",
  "buttonTitles.iUnderStand": "なるほど",
  "buttonTitles.joinNow": "Join now",
  "buttonTitles.learnMore": "もっと詳しく知る",
  "buttonTitles.manageTokens": "トークンを管理",
  "buttonTitles.masterPasswordCheckbox": "SubWallet ではこのパスワードを回復できないことを理解しています。",
  "buttonTitles.newConnection": "新しい接続",
  "buttonTitles.next": "次",
  "buttonTitles.notNow": "Not now",
  "buttonTitles.rateSubwallet": "Rate SubWallet",
  "buttonTitles.reload": "Reload",
  "buttonTitles.remove": "削除",
  "buttonTitles.removeThisAcc": "このアカウントを削除",
  "buttonTitles.resetSorting": "並べ替えをリセット",
  "buttonTitles.save": "保存",
  "buttonTitles.saveItSomeWhereSafe": "私はそれをどこかに安全に保管してあります。",
  "buttonTitles.scanQrCode": "QRコードをスキャン",
  "buttonTitles.scrollInstruction": "スクロールしてすべてのセクションを読みます",
  "buttonTitles.seeMore": "続きを見る",
  "buttonTitles.send": "送信",
  "buttonTitles.sendFeedback": "Send feedback",
  "buttonTitles.stake": "ステーク",
  "buttonTitles.stakeMore": "もっとステーク",
  "buttonTitles.startStaking": "Start staking",
  "buttonTitles.transfer": "転送",
  "buttonTitles.transferAll": "すべてを転送",
  "buttonTitles.unblock": "ブロックを解除",
  "buttonTitles.unbond": "アンボンド",
  "buttonTitles.unlock": "ロックを解除",
  "buttonTitles.unlockWithBiometric": "Unlock with your biometric",
  "buttonTitles.unstake": "アンステーク",
  "buttonTitles.update": "Update",
  "buttonTitles.uploadFromPhotos": "写真からアップロード",
  "buttonTitles.viewAccOnExplorer": "エクスプローラーでアカウントを表示",
  "buttonTitles.viewTransaction": "トランザクションを表示",
  "buttonTitles.withdraw": "Withdraw",
  "buttonTitles.withDrawUnstakedFunds": "アンステーク資金を引き出す",
  "buyTokens.buyTokensMessage": "このトランザクションを完了するために、選択したサプライヤーに移動します",
  "common.account": "アカウント",
  "common.accountAddress": "アカウントアドレス",
  "common.accountConnected": "アカウント接続済み",
  "common.accountName": "アカウント名",
  "common.active": "アクティブ",
  "common.addNftSuccess": "NFTコレクションを正常に追加しました",
  "common.address": "アドレス",
  "common.addToFavourites": "お気に入りに追加",
  "common.addToken": "トークンを追加",
  "common.all": "すべて",
  "common.allAccounts": "すべてのアカウント",
  "common.allParachains": "すべてのパラチェーン",
  "common.allProjects": "すべてのプロジェクト",
  "common.amount": "額",
  "common.and": " and ",
  "common.anErrorHasOccurred": "エラーが発生しました。",
  "common.appLock": "アプリロック",
  "common.approveRequestMessage": "アプリを信頼する場合にのみ、このリクエストを承認してください",
  "common.approveTransactionMessage": "リクエスト送信トランザクションを承認しています",
  "common.attachAccount": "アカウントをアタッチ",
  "common.autoConnectDAppAfterCreating": "アカウント作成後にdAppsを自動接続",
  "common.autoLock": "オートロック",
  "common.back": "戻る",
  "common.backToHome": "ホームに戻る",
  "common.block": "このサイトをブロック",
  "common.bundleENV": "Bundle environment: ",
  "common.bytes": "バイト",
  "common.cancel": "キャンセル",
  "common.cancelTask": "タスクをキャンセル",
  "common.cannotScanQRCodeWithoutPermission": "カメラにQRコード読み取り権限を与えてください。",
  "common.chainConnected": "{0} は接続されました",
  "common.chooseAccount": "接続したいアカウントを選択してください",
  "common.close": "閉じる",
  "common.closeAll": "すべてを閉じる",
  "common.collator": "コレーター",
  "common.confirm": "確認",
  "common.connect": "接続",
  "common.connectAll": "すべてを接続",
  "common.connecting": "接続中...",
  "common.continue": "続く",
  "common.copiedToClipboard": "クリップボードにコピーされました",
  "common.copyToClipboard": "クリップボードにコピー",
  "common.createWalletNotification": "あなたのウォレット名は、このアプリケーションのローカルでのみ使用されます。後で編集することができます",
  "common.crowdloanStatus": "クラウドローンステータス",
  "common.currentPassword": "現在のパスワード",
  "common.dApp": "dApp",
  "common.data": "データ",
  "common.days": "日々",
  "common.decimals": "小数",
  "common.desktopMode": "Desktop Mode",
  "common.destinationChain": "宛先チェーン",
  "common.destroying": "破壊しています",
  "common.detail": "詳細",
  "common.devMode": "Dev Mode",
  "common.disconnectAll": "すべてを切断",
  "common.done": "終了",
  "common.emptyBrowserMessage": "URLを入力するか、Webを検索",
  "common.emptyBrowserTabsMessage": "ブラウジングタブがここに表示されます",
  "common.enableChain": "チェーンを有効にしますか？",
  "common.enableChainMessage": "選択したチェーン  ({0})は現在無効になっています。あなたはそれを有効にする必要があります",
  "common.enterPinToUnlock": "ロックを解除するにはPINを入力",
  "common.enterYourPassword": "パスワードを入力してください",
  "common.enterYourPrivateKey": "秘密鍵を入力または貼り付けます",
  "common.eraseAll": "すべてを消去",
  "common.evmNetworks": "EVM ネットワーク",
  "common.explorer": "エクスプローラ",
  "common.fail": "失敗",
  "common.favorites": "お気に入り",
  "common.favouritesEmptyListPlaceholder": "お気に入りがここに表示されます",
  "common.fee": "手数料：",
  "common.finish": "終了",
  "common.firstScreenMessagePart1": "続行することにより、あなたは私たちの以下の事項に同意したものとみなされます。",
  "common.firstScreenMessagePart2": "利用規約とプライバシーポリシー",
  "common.forgetAll": "サイトの情報をすべて消去する",
  "common.forgetSite": "サイトの情報を消去する",
  "common.forgotPassword": "パスワードをお忘れですか ？",
  "common.from": "送信元",
  "common.genesis": "起源",
  "common.goToSetting": "設定に移動",
  "common.hexData": "Hex データ",
  "common.history": "ヒストリー",
  "common.historyEmptyListPlaceholder": "あなたの履歴はここに現れます",
  "common.hours": "時間",
  "common.immortal": "immortal",
  "common.immortalValidFrom": "mortal, valid from",
  "common.importAlreadyAccount": "既存のアカウントをインポート",
  "common.importTokenSuccessMessage": "あなたの変更は正常に保存されました",
  "common.info": "情報",
  "common.input": "入力",
  "common.kusamaParachain": "Kusama パラチェーン",
  "common.lastBackup": "Last backup: ",
  "common.lastMigration": "Last migration: ",
  "common.lastRestore": "Last restore: ",
  "common.ledgerAccount": "Ledger アカウント",
  "common.lifetime": "ライフタイム",
  "common.locked": "ロックされています",
  "common.manageTokenList": "トークンリストを管理",
  "common.max": "最大",
  "common.message": "メッセージ",
  "common.method": "方法",
  "common.network": "ネットワーク",
  "common.networkFee": "ネットワーク手数料",
  "common.networks": "ネットワーク",
  "common.newPinCode": "新しいPINコード",
  "common.noAvailableAccount": "利用可能なアカウントはありません",
  "common.noFaceIdPermission": "This app use Face ID to unlock password",
  "common.nominate": "ノミネート",
  "common.nonce": "ノンス",
  "common.normalAccount": "通常のアカウント",
  "common.notify": "通知！",
  "common.ok": "OK",
  "common.on": "の上",
  "common.open": "Open",
  "common.openInBrowser": "ブラウザで開く",
  "common.originChain": "オリジンチェーン",
  "common.parachain": "パラチェーン",
  "common.password": "パスワード",
  "common.pinCode": "PIN コード",
  "common.pleaseUpdateAndroidSystemWebView": "本アプリを引き続きご利用いただくために、Android System Webviewをアップデートしてください",
  "common.polkadotParachain": "Polkadot パラチェーン",
  "common.pools": "プール",
  "common.privacyPolicy": "プライバシーポリシー",
  "common.privateKey": "秘密鍵",
  "common.processing": "処理中...",
  "common.provider": "プロバイダー",
  "common.qrSignerAccount": "QR署名者アカウント",
  "common.ratingAlertMessage": "If you find SubWallet helpful, please take a moment to rate it in the App Store. We appreciate your ratings and your feedback, as we strive to make SubWallet better everyday.",
  "common.ratingAlertTitle": "Rate our app!",
  "common.rawData": "Raw データ",
  "common.received": "受信済み",
  "common.receiveModalText": "支払先アドレスをスキャンする",
  "common.recipient": "受信者",
  "common.reject": "拒否",
  "common.reloadBackground": "バックグラウンドでリロードする",
  "common.removeFromFavourites": "お気に入りから削除",
  "common.repeatPinCode": "PIN コードを繰り返",
  "common.repeatWalletPassword": "ウォレットのパスワードを繰り返し",
  "common.resend": "再送信",
  "common.resetAccount": "アカウントをリセット",
  "common.save": "保存",
  "common.scan": "スキャン",
  "common.scanForApprove": "あなたのデバイスのカメラを使って、ハードウェアウォレットに表示されているQRコードをスキャンします",
  "common.scanFromHardwareWallet": "ハードウェアウォレットからアドレスをスキャン",
  "common.scanFromWallet": "ウォレットからアドレスをスキャン",
  "common.scanQr": "QRをスキャン",
  "common.scanQrPayload": "このデバイスのカメラを使って、もう一方のウォレットに表示されているQRコードをスキャンします",
  "common.scanSignatureToSignMessage": "他のウォレットでこのQRコードをスキャンし、メッセージに署名してください",
  "common.scanSignatureToSignTransaction": "他のウォレットでこのQRコードをスキャンし、取引に署名してください",
  "common.search": "検索",
  "common.searchAtDuckDuckGo": "DuckDuckGoで検索",
  "common.searchPlaceholder": "検索またはWebサイトを入力",
  "common.searchResult": "検索結果",
  "common.searchStakingValidator": "{0}を検索",
  "common.seeAll": "すべてを見る",
  "common.selectAll": "すべて選択",
  "common.selectedValidators": "選択された ({0}) バリデーター",
  "common.selectStakingValidator": "{0}を選択",
  "common.send": "送信",
  "common.sender": "送信者",
  "common.sendFromAddress": "アドレスから送信",
  "common.sending": "送信...",
  "common.sendToAddress": "アドレスに送信",
  "common.share": "共有",
  "common.signMethod": "署名の方法",
  "common.specVersion": "スペックバージョン",
  "common.stakingValidatorDetail": "{0}詳細",
  "common.startOver": "やり直してください",
  "common.status": "スターテス:",
  "common.submit": "送信",
  "common.submitting": "提出中...",
  "common.substrateNetworks": "Substrate ネットワーク",
  "common.symbol": "シンボル",
  "common.termAndConditions": "利用規約",
  "common.tip": "ヒント",
  "common.to": "宛先",
  "common.toImportNFT": "NFTをインポート",
  "common.toImportToken": "トークンをインポート",
  "common.tooManyAttemps": "Too many failed attempts. Please try again later or enter password.",
  "common.toSendAsset": "資産を送信",
  "common.toSendFund": "資金を送る",
  "common.toSendNFT": "NFTを送信",
  "common.total": "合計",
  "common.transferable": "転送可能:",
  "common.transferFailMessage1": "リクエストに問題が発生しました。履歴ページで進捗状況を確認できます。",
  "common.transferFailMessage2": "あなたのリクエストに問題がありました。",
  "common.transferNotSupportedForNetwork": "このネットワークの転送はサポートされていません。",
  "common.transferSuccessMessage": "リクエストが確認されました。履歴ページで進捗状況を確認できます。",
  "common.type": " type",
  "common.unblock": "このサイトのブロックを解除",
  "common.unknownAccount": "不明なアカウント",
  "common.unsupportedToken": "サポートされていないトークン",
  "common.updateChainMessage": "Your selected network has lost connection. Update it by re-enabling it or changing network provider.",
  "common.url": "URL: ",
  "common.useDeviceHaveGooglePlayStore": "本アプリを引き続きご利用いただくには、Google Playストアがインストールされた端末をご利用ください",
  "common.useHardWalletToScan": "Use your hardware wallet's camera\nto scan this QR code",
  "common.useNormalWalletScan": "このQRコードをウォレットでスキャン",
  "common.validator": "バリデーター",
  "common.version": "バージョン:",
  "common.versionLabel": "バージョン",
  "common.viewDetail": "詳細を表示",
  "common.viewDetails": "詳細を見る",
  "common.viewHistory": "履歴を表示",
  "common.viewOnExplorer": "エクスプローラーの表示",
  "common.viewTransaction": "トランザクションを表示",
  "common.walletName": "ウォレット名",
  "common.walletPassword": "ウォレットのパスワード",
  "common.watchOnlyAccount": "ウォッチのみのアカウントをアタッチ",
  "common.win": "勝つ",
  "common.year": "年",
  "common.youDonotHaveAnyAcc": "接続できる{0}アカウントがありません。新しいアカウントを作成してください。",
  "confirmation.addNetworkRequest": "ネットワークリクエストを追加",
  "confirmation.addTokenRequest": "トークンリクエストを追加",
  "confirmation.approveRequest": "リクエストを承認",
  "confirmation.blockExplorer": "ブロックエクスプローラー",
  "confirmation.chainId": "チェーンID",
  "confirmation.chainType": "チェーンタイプ",
  "confirmation.contractAddress": "コントラクトアドレス",
  "confirmation.crowdloanURL": "クラウドローンURL",
  "confirmation.deleteContactMessage": "アドレス帳にこのアドレスが表示されなくなります",
  "confirmation.deleteContactTitle": "この連絡先を削除しますか？",
  "confirmation.fromAccount": "アカウントから",
  "confirmation.immortal": "immortal",
  "confirmation.lifeTimeContent": "mortal, valid from {{0}} to {{1}}",
  "confirmation.messageDetail": "メッセージの詳細",
  "confirmation.metadataDescription": "この更新を承認すると、{0}から{1}チェーンのメタデータが同期されます。",
  "confirmation.notSpMessagePart1": "この機能は利用できません",
  "confirmation.notSpMessagePart2": "Please change to another account type",
  "confirmation.providerUrl": "プロバイダーURL",
  "confirmation.requestWithAccount": "あなたはアカウントでリクエストを承認しています",
  "confirmation.signatureRequest": "署名依頼",
  "confirmation.siteBlocked": "このサイトはブロックされています",
  "confirmation.siteBlockedMessage": "このサイトは以前にブロックされています。ブロックを解除してアクセスを許可か？",
  "confirmation.siteConnected": "このサイトには以下のアカウントが接続されています。",
  "confirmation.siteNotConnected": "このサイトに接続されていません",
  "confirmation.siteNotConnectedMessage": "SubWallet はこのサイトに接続されていません。接続するには、ウェブサイトの「ウォレットを接続する」ボタンを押してください",
  "confirmation.toAccount": "アカウントへ",
  "confirmation.toContract": "コントラクトへ",
  "confirmation.tokenType": "トークンタイプ",
  "confirmation.transactionDetail": "トランザクションの詳細",
  "confirmation.yourMetadataIsOutOfDate": "あなたのメタデータは古くなっています",
  "createAccount.createWithNewSeedPhrase": "新しいシードフレーズで作成",
  "createAccount.deriveFromAnExistingAcc": "既存のアカウントから派生",
  "createAccount.ethereum": "Ethereum",
  "createAccount.polkadot": "Polkadot",
  "createPassword.createPasswordMessage": "このパスワードを使用して、アカウントのロックを解除",
  "cryptoScreen.address": "アドレス",
  "cryptoScreen.buy": "購入",
  "cryptoScreen.receive": "受信",
  "cryptoScreen.send": "送信",
  "cryptoScreen.swap": "スワップ",
  "customization.balance": "残高",
  "customization.networks": "ネットワーク",
  "customization.showZeroBalance": "残高０を表示",
  "emptyScreen.browserEmptyMessage": "以前にウェブサイトを検索したことがありません",
  "emptyScreen.browserEmptyTitle": "最近の検索はなし",
  "emptyScreen.categoryItemEmpty": "このカテゴリは空です",
  "emptyScreen.crowdloanEmptyMessage": "クラウドローンはこちらに表示されます！",
  "emptyScreen.crowdloanEmptyTitle": "クラウドローンはありません",
  "emptyScreen.groupEmptyMessage": "Change your search and try again",
  "emptyScreen.groupEmptyTitle": "No earning option found",
  "emptyScreen.historyEmptyMessage": "トランザクションの履歴がここに表示されます！",
  "emptyScreen.historyEmptyTitle": "トランザクションは見つかりませんでした",
  "emptyScreen.manageDAppDetailEmptyMessage": "接続されたアカウントのリストがここに表示されます。",
  "emptyScreen.manageDAppDetailEmptyTitle": "接続されたアカウントはありません",
  "emptyScreen.manageDAppEmptyMessage": "承認されたdAppsのリストはここに表示されます。",
  "emptyScreen.manageDAppEmptyTitle": "dAppは見つかりません",
  "emptyScreen.missionPoolsEmptyMessage": "Your missions will show up here",
  "emptyScreen.missionPoolsEmptyTitle": "No mission found",
  "emptyScreen.networkSettingsMessage": "ネットワークがここに表示されます。",
  "emptyScreen.networkSettingsTitle": "ネットワークは見つかりません",
  "emptyScreen.nftEmptyMessage": "右上隅の[+]をクリックしてNFTをインポート",
  "emptyScreen.nftEmptyTitle": "NFTsは見つかりません",
  "emptyScreen.poolEmptyMessage": "Change your search and try again",
  "emptyScreen.poolEmptyTitle": "No earning option found",
  "emptyScreen.positionEmptyMessage": "Change your search or explore other earning options",
  "emptyScreen.positionEmptyTitle": "No earning position found",
  "emptyScreen.selectorEmptyMessage": "検索条件を変更して、もう一度お試しください",
  "emptyScreen.selectorEmptyTitle": "結果が見つかりません",
  "emptyScreen.stakingEmptyMessage": "あなたのステーキングアカウントがここに表示されます！",
  "emptyScreen.stakingEmptyTitle": "ステーキングはありません",
  "emptyScreen.tokenEmptyMessage": "トークンを追加して始める",
  "emptyScreen.tokenEmptyMessageV2": "Try searching or importing one",
  "emptyScreen.tokenEmptyTitle": "トークンは見つかりません",
  "emptyScreen.walletConnectDetailEmptyTitle": "dAppが見つからりません",
  "emptyScreen.walletConnectEmptyDetailMessage": "承認されたdAppはここに表示されます。",
  "errorMessage.amountMustBeEqualOrLessThan": "金額は{0} 以下でなければなりません",
  "errorMessage.amountMustBeGreaterThanZero": "金額は0より大きくなければなりません",
  "errorMessage.amountRequiredError": "金額が必要です",
  "errorMessage.blockExplorerMustBeAValidUrl": "ブロックエクスプローラーは有効なURLである必要があります",
  "errorMessage.cannotConnectToThisProvider": "このプロバイダーに接続できません",
  "errorMessage.connectionAlreadyExist": "接続はすでに存在する",
  "errorMessage.contactAddressIsRequired": "連絡先アドレスが必要です",
  "errorMessage.contactNameIsRequired": "連絡先名が必要です",
  "errorMessage.contactNameMustBeUnique": "連絡先名は一意でなければなりません",
  "errorMessage.crowdloanUrlMustBeAValidUrl": "クラウドローンURLは有効なURLでなければなりません",
  "errorMessage.errorConfigureNetwork": "ネットワークを設定時のエラー",
  "errorMessage.externalAccount": "外部アカウントがあります",
  "errorMessage.failToAddConnection": "接続の追加に失敗",
  "errorMessage.framesToBig": "フレーム数が大きすぎるため、QRは外部Rawデータとして認識されていないようです",
  "errorMessage.invalidAddress": "無効なアドレス",
  "errorMessage.invalidAmount": "金額は無効です",
  "errorMessage.invalidContactAddress": "無効な連絡先アドレス",
  "errorMessage.invalidContractForSelectedChain": "選択したチェーンの無効なコントラクト",
  "errorMessage.invalidEvmContractAddress": "無効なEVMコントラクトアドレス",
  "errorMessage.invalidMasterPassword": "無効なマスターパスワード",
  "errorMessage.invalidMnemonicSeed": "無効なニーモニックシード",
  "errorMessage.invalidPassword": "無効なパスワード",
  "errorMessage.invalidPinCode": "無効なPIN コード",
  "errorMessage.invalidProviderUrl": "プロバイダーURLは無効です",
  "errorMessage.invalidRecipientAddress": "無効な受信者アドレス",
  "errorMessage.isNotAnAddress": "無効です。写真にアドレスが含まれていません。",
  "errorMessage.isNotContractAddress": "不正。写真にコントラクトアドレスが含まれていません。",
  "errorMessage.networkDisconected": "切断されています",
  "errorMessage.networkHasBeenAlreadyAdded": "このネットワークはすでに追加されています",
  "errorMessage.noNetwork": "SubWalletは現在、Genesis Hashのあるチェーンを認識していません。最初にネットワークを追加してください",
  "errorMessage.noProviderAvailable": "利用可能なプロバイダーなし",
  "errorMessage.noSenderFound": "アプリ内に関連するアカウントはありません",
  "errorMessage.notSameAddressTypeError": "受信者アドレスは、現在のアカウントアドレスと同じタイプでなければなりません",
  "errorMessage.occurredError": "エラーが発生しました。後でもう一度やり直してください",
  "errorMessage.providerHasExisted": "このプロバイダーが存在しています",
  "errorMessage.providerIsNotTheSameNetwork": "このプロバイダーは同じネットワークではありません",
  "errorMessage.providerRequirePrefix": "プロバイダーURLには、http/httpsまたはwssプレフィックスが必要です",
  "errorMessage.qrCodeNotSupport": "QRコードはサポートされていません。サポートされているソフトウェアからトランザクションをスキャンしていることを確認してください",
  "errorMessage.recipientAddressIsRequired": "受信者アドレスが必要です",
  "errorMessage.recipientAddressMustBeType": "受信者アドレスは{0}タイプでなければなりません",
  "errorMessage.sameAddressError": "受信者のアドレスは、送信者アドレスと同じではありません",
  "errorMessage.scanAgain": "申し訳ありませんが、問題が発生しました。\nもう一度スキャンしてください。",
  "errorMessage.successfullyAddANewCustomProvider": "新しいカスタムプロバイダーを正常に追加しました",
  "errorMessage.thisChainHasAlreadyBeenAdded": "このチェーンはすでに追加されています",
  "errorMessage.thisProviderHasAlreadyBeenAdded": "This provider has already been added",
  "errorMessage.thisProviderIsNotForThisNetwork": "このプロバイダーはこのネットワークの対象外です",
  "errorMessage.tokenAlreadyAdded": "このトークンはすでに追加されています",
  "errorMessage.unableToConnectToTheProvider": "プロバイダーに接続できません",
  "errorMessage.unbondInvalidAmount": "無効です。あなたがこの額をアンステークした場合、ステーキングは必要最小ステークを下回ることになります",
  "errorMessage.unbondMustBeEqual": "{0}は{1}と等しくなければなりません",
  "errorMessage.unbondMustBeEqualOrGreaterThan": "{0} は{1}より大きくなければなりません",
  "errorMessage.unbondMustBeEqualOrLessThan": "{0} は{1}以下でなければならなりません",
  "errorMessage.unbondMustBeGreaterThanZero": "{0} は0より大きくなければなりません",
  "errorMessage.unknownError": "エラーが発生しました。もう一度やり直してください。",
  "errorMessage.unreadableQrCode": "QRコードが読み取れません。別のQRコードを読み取ってください。",
  "errorMessage.validateProviderError": "このプロバイダーの検証エラー",
  "errorMessage.wrongPassword": "間違ったパスワード",
  "exportAccount.exportJsonFile": "JSONファイルをエクスポート",
  "exportAccount.exportJsonFileSuccessfulMessage": "このアカウントのJSONファイルのエクスポートに成功しました。",
  "exportAccount.exportPrivateKey": "秘密鍵をエクスポート",
  "exportAccount.exportQRCode": "QRコードをエクスポート",
  "exportAccount.exportSeedPhrase": "シードフレーズをエクスポート",
  "exportAccount.exportSuccessful": "エクスポートが成功",
  "exportAccount.yourJsonFile": "あなたのJSONファイル",
  "filterOptions.blockedDApp": "ブロックされたdApp",
  "filterOptions.claimStakingReward": "ステーキング報酬を請求",
  "filterOptions.connectedDApp": "接続されたdApp",
  "filterOptions.customChains": "カスタムチェーン",
  "filterOptions.customTokens": "カスタムトークン",
  "filterOptions.directNomination": "Direct nomination",
  "filterOptions.disabledChains": "無効なチェーン",
  "filterOptions.disabledTokens": "無効なトークン",
  "filterOptions.enabledChains": "有効なチェーン",
  "filterOptions.enabledTokens": "有効なトークン",
  "filterOptions.evmChains": "EVMチェーン",
  "filterOptions.evmDApp": "EVM の dApp",
  "filterOptions.fail": "失敗",
  "filterOptions.failed": "失敗した",
  "filterOptions.inAuction": "In auction",
  "filterOptions.kusamaParachain": "Kusama パラチェーン",
  "filterOptions.lending": "Lending",
  "filterOptions.liquidStaking": "Liquid staking",
  "filterOptions.mainnet": "Mainnet",
  "filterOptions.nftTransaction": "NFTトランザクション",
  "filterOptions.nominated": "ノミネーション",
  "filterOptions.nominationPool": "Nomination pool",
  "filterOptions.parachainStaking": "Parachain staking",
  "filterOptions.polkadotParachain": "Polkadot パラチェーン",
  "filterOptions.pooled": "プール",
  "filterOptions.receiveToken": "トークンを受信",
  "filterOptions.sendToken": "トークンを送信",
  "filterOptions.singleFarming": "Single farming",
  "filterOptions.stakeTransaction": "ステークトランザクション",
  "filterOptions.substrateChains": "Sbstrate チェーン",
  "filterOptions.substrateDApp": "Substrate dApp",
  "filterOptions.successful": "成功",
  "filterOptions.testnet": "Testnet",
  "filterOptions.won": "Won",
  "header.accessConfiguration": "アクセス設定",
  "header.accountDetails": "アカウント詳細",
  "header.accounts": "アカウント",
  "header.actions": "アクション",
  "header.addContact": "連絡先を追加",
  "header.addNetworkRequest": "ネットワークリクエストを追加",
  "header.addNewProvider": "新しいプロバイダーを追加",
  "header.addressBook": "アドレス帳",
  "header.addToBond": "ボンドに追加",
  "header.addToBondConfirm": "ボンドへ追加する確認",
  "header.addTokenRequest": "トークンリクエストを追加",
  "header.applyMasterPassword": "マスターパスワードを適用",
  "header.attachAnAcc": "アカウントをアタッチ",
  "header.attachReadOnlyAcc": "ウォッチのみのアカウントをアタッチ",
  "header.buyToken": "トークンを購入",
  "header.cancelUnstake": "アンステークスをキャンセル",
  "header.cancelUnstakeConfirmation": "アンステークスのキャンセルの確認",
  "header.changePassword": "パスワードを変更",
  "header.claimRewards": "報酬を請求する",
  "header.claimRewardsConfirmation": "報酬請求の確認",
  "header.claimStakingReward": "ステーキング報酬を請求",
  "header.confirmation": "確認",
  "header.confirmTransfer": "転送を確認",
  "header.connectedNetworks": "接続されたネットワーク",
  "header.connectKeystoneDevice": "Keystone デバイスを接続",
  "header.connectLedgerDevice": "Ledger デバイスを接続",
  "header.connectPolkadotVault": "Polkadot Vaultを接続",
  "header.connectSubwallet": "SubWallet を接続",
  "header.connectWebsite": "Webサイトを接続",
  "header.connectWithSubwallet": "SubWallet で接続",
  "header.createAPassword": "パスワードを作成",
  "header.createMasterPassword": "マスターパスワードを作成",
  "header.createNewAcc": "新しいアカウントを作成",
  "header.crowdloans": "クラウドローン",
  "header.currentPassword": "現在のパスワード",
  "header.customizeAssetDisplay": "資産表示のカスタマイズ",
  "header.dAppConfiguration": "dApp設定",
  "header.deleteNetwork": "ネットワークを削除",
  "header.deleteNft": "NFTを削除",
  "header.deleteToken": "トークンを削除",
  "header.description": "説明",
  "header.disconnect": "切断",
  "header.earning": "Earning",
  "header.editContact": "連絡先を編集",
  "header.enterPassword": "パスワードを入力",
  "header.exportAccount": "エクスポートアカウント",
  "header.filter": "フィルター",
  "header.generalSettings": "一般設定",
  "header.generalTermTitle": "利用規約",
  "header.groupList": "Earning options",
  "header.history": "ヒストリー",
  "header.importAcc": "アカウントをインポート",
  "header.importByPrivateKey": "秘密鍵によるインポート",
  "header.importByQRCode": "QRコードでインポート",
  "header.importFromJson": "Polkadot.js からのインポート",
  "header.importFromSeedPhrase": "シードフレーズからのインポート",
  "header.importNetwork": "ネットワークをインポート",
  "header.importNft": "NFTをインポート",
  "header.importToken": "トークンをインポート",
  "header.language": "言語",
  "header.manageAddressBook": "アドレス帳を管理",
  "header.manageNetworks": "ネットワークを管理",
  "header.manageTokens": "トークンを管理",
  "header.manageWebsiteAccess": "ウェブサイトへのアクセスを管理",
  "header.messageDetails": "メッセージの詳細",
  "header.mintLDOT": "Mint LDOT",
  "header.mintLDOTTransaction": "Mint LDOT transaction",
  "header.mintQDOT": "Mint qDOT",
  "header.mintQDOTTransaction": "Mint qDOT transaction",
  "header.mintSDOT": "Mint sDOT",
  "header.mintSDOTTransaction": "Mint sDOT transaction",
  "header.mintSTDOT": "Mint stDOT",
  "header.mintSTDOTTransaction": "Mint stDOT transaction",
  "header.mintVDOT": "Mint vDOT",
  "header.mintVDOTTransaction": "Mint vDOT transaction",
  "header.missionPools": "Mission Pools",
  "header.networkDetails": "ネットワークの詳細",
  "header.newPassword": "新しいパスワード",
  "header.nftTransaction": "NFTトランザクション",
  "header.nftTransferConfirmation": "NFT転送の確認",
  "header.nominationDetails": "ノミネーションの詳細",
  "header.notificationType": "通知タイプ",
  "header.poolDetails": "プールされた詳細",
  "header.poolList": "{{symbol}} earning options",
  "header.positionList": "Your earning positions",
  "header.providers": "プロバイダー",
  "header.receiveToken": "トークンを受信",
  "header.redeemLDOT": "Redeem LDOT",
  "header.redeemLDOTTransaction": "Redeem LDOT transaction",
  "header.redeemQDOT": "Redeem qDOT",
  "header.redeemQDOTTransaction": "Redeem qDOT transaction",
  "header.redeemSDOT": "Redeem sDOT",
  "header.redeemSDOTTransaction": "Redeem sDOT transaction",
  "header.redeemSTDOT": "Redeem stDOT",
  "header.redeemSTDOTTransaction": "Redeem stDOT transaction",
  "header.redeemVDOT": "Redeem vDOT",
  "header.redeemVDOTTransaction": "Redeem vDOT transaction",
  "header.removeThisAcc": "このアカウントを削除？",
  "header.scanQR": "QRコードをスキャン",
  "header.search": "検索",
  "header.securitySettings": "セキュリティ設定",
  "header.selectAccount": "アカウントを選択",
  "header.selectAccType": "アカウントタイプを選択",
  "header.selectCollator": "コレーターを選択",
  "header.selectNetwork": "ネットワークを選択",
  "header.selectPool": "プールを選択",
  "header.selectToken": "トークンを選択",
  "header.selectTokenType": "トークンタイプを選択",
  "header.selectValidator": "バリデーターを選択",
  "header.sendToken": "トークンを送信",
  "header.settings": "設定",
  "header.signatureRequest": "署名依頼",
  "header.signatureRequired": "署名が必要",
  "header.sorting": "並べ替え",
  "header.stake": "Stake",
  "header.staking": "ステーキング",
  "header.successful": "成功",
  "header.supply": "Supply",
  "header.switchNetworkRequest": "ネットワークリクエストを切り替えます",
  "header.tokenApprove": "Token approve",
  "header.tokenApproveTransaction": "Token approve transaction",
  "header.tokenDetails": "トークンの詳細",
  "header.transactionConfirmation": "Transaction confirm",
  "header.transactionRequest": "トランザクションリクエスト",
  "header.transfer": "転送",
  "header.transferConfirmation": "転送確認",
  "header.transferNft": "NFTを転送",
  "header.unbond": "アンボンド",
  "header.unbondConfirmation": "アンボンドの確認",
  "header.unstake": "Unstake",
  "header.unstakeLDOT": "Unstake LDOT",
  "header.unstakeLDOTTransaction": "Unstake LDOT transaction",
  "header.unstakeQDOT": "Unstake qDOT",
  "header.unstakeQDOTTransaction": "Unstake qDOT transaction",
  "header.unstakeRequest": "アンステークスのリクエスト",
  "header.unstakeSDOT": "Unstake sDOT",
  "header.unstakeSDOTTransaction": "Unstake sDOT transaction",
  "header.unstakeSTDOT": "Unstake stDOT",
  "header.unstakeSTDOTTransaction": "Unstake stDOT transaction",
  "header.unstakeTransaction": "アンステークストランザクション",
  "header.unstakeVDOT": "Unstake vDOT",
  "header.unstakeVDOTTransaction": "Unstake vDOT transaction",
  "header.updateChain": "Update network",
  "header.updateMetadata": "メタデータを更新",
  "header.validatorDetails": "バリデーターの詳細",
  "header.verifySeedPhrase": "シードフレーズを確認",
  "header.walletConnect": "WalletConnect",
  "header.walletTheme": "ウォレットのテーマ",
  "header.websiteAccess": "ウェブサイトへのアクセス",
  "header.websiteAccessConfig": "ウェブサイトのアクセス設定",
  "header.withDraw": "引き出し",
  "header.withdrawalConfirm": "引き出しの確認",
  "header.withdrawStake": "ステークを引き出す",
  "header.yourAddress": "あなたのアドレス",
  "header.yourCollections": "あなたのコレクション",
  "header.yourPrivateKey": "あなたの秘密鍵",
  "header.yourQrCode": "あなたのQRコード",
  "header.yourRecoveryPhrase": "あなたのリカバリーフレーズ",
  "header.yourSeedPhrase": "あなたのシードフレーズ",
  "historyScreen.extrinsicStatus.cancelled": "キャンセルされた",
  "historyScreen.extrinsicStatus.completed": "完了しました",
  "historyScreen.extrinsicStatus.failed": "失敗した",
  "historyScreen.extrinsicStatus.processing": "処理中...",
  "historyScreen.extrinsicStatus.queued": "キュー",
  "historyScreen.extrinsicStatus.submitting": "提出中",
  "historyScreen.extrinsicStatus.unknown": "不明",
  "historyScreen.extrinsicType.bond": "ボンド",
  "historyScreen.extrinsicType.cancelUnstake": "アンステークスをキャンセル",
  "historyScreen.extrinsicType.claimReward": "報酬を請求",
  "historyScreen.extrinsicType.compounding": "複利",
  "historyScreen.extrinsicType.crowdloan": "クラウドローン",
  "historyScreen.extrinsicType.evmExecute": "EVM実行",
  "historyScreen.extrinsicType.mintLDOT": "Mint LDOT",
  "historyScreen.extrinsicType.mintQDOT": "Mint qDOT",
  "historyScreen.extrinsicType.mintSDOT": "Mint sDOT",
  "historyScreen.extrinsicType.mintSTDOT": "Mint stDOT",
  "historyScreen.extrinsicType.mintVDOT": "Mint vDOT",
  "historyScreen.extrinsicType.nft": "NFT",
  "historyScreen.extrinsicType.redeemLDOT": "Redeem LDOT",
  "historyScreen.extrinsicType.redeemQDOT": "Redeem qDOT",
  "historyScreen.extrinsicType.redeemSDOT": "Redeem sDOT",
  "historyScreen.extrinsicType.redeemSTDOT": "Redeem stDOT",
  "historyScreen.extrinsicType.redeemVDOT": "Redeem vDOT",
  "historyScreen.extrinsicType.stake": "ステーク",
  "historyScreen.extrinsicType.tokenApprove": "Token approve",
  "historyScreen.extrinsicType.transfer": "転送",
  "historyScreen.extrinsicType.unbond": "アンボンド",
  "historyScreen.extrinsicType.unstake": "アンステーク",
  "historyScreen.extrinsicType.unstakeLDOT": "Unstake LDOT",
  "historyScreen.extrinsicType.unstakeQDOT": "Unstake qDOT",
  "historyScreen.extrinsicType.unstakeSDOT": "Unstake sDOT",
  "historyScreen.extrinsicType.unstakeSTDOT": "Unstake stDOT",
  "historyScreen.extrinsicType.unstakeVDOT": "Unstake vDOT",
  "historyScreen.extrinsicType.withdraw": "引き出し",
  "historyScreen.label.amount": "額",
  "historyScreen.label.cancelUnstakeValue": "アンステークの額をキャンセル",
  "historyScreen.label.collectionName": "コレクション名",
  "historyScreen.label.contributeBalance": "クラウドローン残高",
  "historyScreen.label.destinationFee": "宛先手数料",
  "historyScreen.label.estimatedReceivables": " Estimated receivables",
  "historyScreen.label.extrinsicHash": "外部ハッシュ",
  "historyScreen.label.fromAccount": "アカウントから",
  "historyScreen.label.minimumReceivables": "Minimum receivables",
  "historyScreen.label.network": "ネットワーク",
  "historyScreen.label.networkFee": "ネットワーク手数料",
  "historyScreen.label.originChainFee": "オリジン・チェーンの手数料",
  "historyScreen.label.stakingType": "ステーキングタイプ",
  "historyScreen.label.stakingValue": "ステーキング額",
  "historyScreen.label.transactionFail": " fail",
  "historyScreen.label.transactionStatus": "トランザクションステータス",
  "historyScreen.label.transactionTime": "トランザクション時間",
  "historyScreen.label.transactionType": "トランザクションタイプ",
  "historyScreen.label.unstakeValue": "アンステーク額",
  "historyScreen.label.withdrawValue": "引き出し額",
  "historyScreen.title.bondTransaction": "ボンドトランザクション",
  "historyScreen.title.cancelUnstakeTransaction": "アンステークランザクションのキャンセル",
  "historyScreen.title.claimRewardTransaction": "報酬の請求トランザクション",
  "historyScreen.title.crowdloanTransaction": "クラウドローントランザクション",
  "historyScreen.title.evmTransaction": "EVMトランザクション",
  "historyScreen.title.mintLDOTTransaction": "Mint LDOT transaction",
  "historyScreen.title.mintQDOTTransaction": "Mint qDOT transaction",
  "historyScreen.title.mintSDOTTransaction": "Mint sDOT transaction",
  "historyScreen.title.mintSTDOTTransaction": "Mint stDOT transaction",
  "historyScreen.title.mintVDOTTransaction": "Mint vDOT transaction",
  "historyScreen.title.nftTransaction": "NFTトランザクション",
  "historyScreen.title.receiveTransaction": "トークンを受信",
  "historyScreen.title.redeemLDOTTransaction": "Redeem LDOT transaction",
  "historyScreen.title.redeemQDOTTransaction": "Redeem qDOT transaction",
  "historyScreen.title.redeemSDOTTransaction": "Redeem sDOT transaction",
  "historyScreen.title.redeemSTDOTTransaction": "Redeem stDOT transaction",
  "historyScreen.title.redeemVDOTTransaction": "Redeem vDOT transaction",
  "historyScreen.title.sendTransaction": "トークンを送信",
  "historyScreen.title.stakeTransaction": "ステークトランザクション",
  "historyScreen.title.tokenApproveTransaction": "Token approve transaction",
  "historyScreen.title.transaction": "トランザクション",
  "historyScreen.title.unbondTransaction": "アンボンドトランザクション",
  "historyScreen.title.unstakeLDOTTransaction": "Unstake LDOT transaction",
  "historyScreen.title.unstakeQDOTTransaction": "Unstake qDOT transaction",
  "historyScreen.title.unstakeSDOTTransaction": "Unstake sDOT transaction",
  "historyScreen.title.unstakeSTDOTTransaction": "Unstake stDOT transaction",
  "historyScreen.title.unstakeTransaction": "アンステークストランザクション",
  "historyScreen.title.unstakeVDOTTransaction": "Unstake vDOT transaction",
  "historyScreen.title.withdrawTransaction": "引き出しトランザクション",
  "importAccount.accounts": "アカウント",
  "importAccount.ethereumAccount": "Ethereumアカウント",
  "importAccount.importAccounts": "{0} のアカウントをインポート",
  "importAccount.importByMetaMaskPrivateKey": "メタマスク秘密鍵によるインポート",
  "importAccount.importByQRCode": "QRコードでインポート",
  "importAccount.importFromJson": "Polkadot.js からのインポート",
  "importAccount.importFromSeedPhrase": "シードフレーズからのインポート",
  "importAccount.importFromSeedPhraseMessage": "既存のアカウントをインポートするには、シードフレーズを入力してください",
  "importAccount.importJsonInputTitle1": "JSONファイルによるインポート",
  "importAccount.importJsonInputTitle2": "クリックまたはドラッグしてファイルを交換",
  "importAccount.importJsonMessage": "Polkadot.js アカウントを作成するときに使用したパスワードを入力してください。",
  "importAccount.importJsonSubtitle": "Polkadot.js からエクスポートしたJSONファイルをドラッグアンドドロップ",
  "importAccount.importPrivateKeyMessage": "既存のウォレットをインポートするには、秘密鍵を入力してください",
  "importAccount.importQrCodeMessage1": "デバイスのカメラへのアクセスをSubWallet に許可していることを確認してください。",
  "importAccount.importQrCodeMessage2": "詳しくは\"QRスキャン\"ボタンをクリックするか、この説明をお読みください。",
  "importAccount.selectAccountType": "アカウントタイプを選択",
  "importAccount.substrateAccount": "Substrateアカウント",
  "importEvmNft.importNft": "NFTをインポート",
  "importEvmNft.nftType": "NFTタイプ",
  "importNetwork.addressPrefix": "アドレスプレフィックス",
  "importNetwork.blockExplorer": "ブロックエクスプローラー",
  "importNetwork.chainName": "チェーン名",
  "importNetwork.chainType": "チェーンタイプ",
  "importNetwork.contractAddress": "コントラクトアドレス",
  "importNetwork.crowdloanUrl": "クラウドローンURL",
  "importNetwork.decimal": "小数",
  "importNetwork.evmChainId": "EVM チェーン ID",
  "importNetwork.paraId": "パラチェーンID",
  "importNetwork.priceId": "プライス ID",
  "importNetwork.providerUrl": "プロバイダーURL",
  "importNetwork.symbol": "シンボル",
  "importNetwork.tokenName": "トークン名",
  "importToken.contractAddress": "コントラクトアドレス",
  "importToken.tokenName": "トークン名",
  "inputLabel.account": "アカウント",
  "inputLabel.accountAddress": "アカウントアドレス",
  "inputLabel.accountName": "アカウント名",
  "inputLabel.activeStaked": "アクティブなステーク",
  "inputLabel.address": "アドレス",
  "inputLabel.amount": "額",
  "inputLabel.arguments": "Arguments",
  "inputLabel.availableBalance": "利用可能残高",
  "inputLabel.availableForWithdraw": "引き出し可能",
  "inputLabel.availableRewards": "利用可能な報酬",
  "inputLabel.bondRewardAfterClaim": "請求後の報酬をボンドする",
  "inputLabel.cancelUnstakeFee": "ステークス料金をキャンセル",
  "inputLabel.chainId": "チェーンID",
  "inputLabel.collator": "コレーター",
  "inputLabel.collectionId": "Collection ID",
  "inputLabel.commission": "コミッション",
  "inputLabel.confirmNewPassword": "新しいパスワードを確認",
  "inputLabel.contractAddress": "コントラクトアドレス",
  "inputLabel.createdBy": "によって作成された",
  "inputLabel.currentPassword": "現在のパスワード",
  "inputLabel.dApp": "dApp",
  "inputLabel.derivativeTokenBalance": "Derivative token balance",
  "inputLabel.description": "説明",
  "inputLabel.destinationNetwork": "宛先ネットワーク",
  "inputLabel.estimatedAnnualEarnings": "推定年間収益",
  "inputLabel.estimatedApy": "推定APY",
  "inputLabel.estimatedEarnings": "推定収益額",
  "inputLabel.estimatedFee": "推定料金",
  "inputLabel.estimateFee": "推定料金",
  "inputLabel.extrinsicHash": "外部ハッシュ",
  "inputLabel.fastUnstake": "Fast Unstake",
  "inputLabel.from": "送信元",
  "inputLabel.fromAccount": "アカウントから",
  "inputLabel.hexData": "Hex データ",
  "inputLabel.maxNomination": "最大ノミネーション",
  "inputLabel.maxValidators": "最大バリデーター数",
  "inputLabel.method": "方法",
  "inputLabel.methodData": "Method data",
  "inputLabel.minimumActive": "最小アクティブ",
  "inputLabel.minimumStaked": "最小ステーク",
  "inputLabel.minStakeRequire": "最低必要ステーク",
  "inputLabel.name": "Name",
  "inputLabel.network": "ネットワーク",
  "inputLabel.networkFee": "ネットワーク手数料",
  "inputLabel.newPassword": "新しいパスワード",
  "inputLabel.nft": "NFT",
  "inputLabel.nftCollectionName": "NFTコレクション名",
  "inputLabel.nftDetails": "NFTの詳細",
  "inputLabel.nftId": "NFT ID",
  "inputLabel.nominationInfo": "Nomination info",
  "inputLabel.nominationStatus": "ノミネーションステータス",
  "inputLabel.originChainFee": "オリジン・チェーンの手数料",
  "inputLabel.ownedBy": "が所有している",
  "inputLabel.ownStake": "自身のステーク",
  "inputLabel.pool": "プール",
  "inputLabel.pooledStatus": "プール状態",
  "inputLabel.recipient": "受信者",
  "inputLabel.rewardAmount": "報酬額",
  "inputLabel.selectAcc": "アカウントを選択",
  "inputLabel.selectAnUnstakeRequest": "アンステークリクエストを選択",
  "inputLabel.selectCollator": "コレーターを選択",
  "inputLabel.selectDestinationChain": "宛先チェーンを選択",
  "inputLabel.selectPool": "プールを選択",
  "inputLabel.selectSupplier": "サプライヤーを選択",
  "inputLabel.selectToken": "トークンを選択",
  "inputLabel.selectValidator": "バリデーターを選択",
  "inputLabel.sender": "送信者",
  "inputLabel.senderNetwork": "送信者ネットワーク",
  "inputLabel.senderTransferableBalance": "送金可能残高",
  "inputLabel.sendFrom": "から送信",
  "inputLabel.sendTo": "に送る",
  "inputLabel.stakeFromOthers": "他からのステーク",
  "inputLabel.stakingAmount": "ステーキング額",
  "inputLabel.stakingStatus": "ステーキングステータス",
  "inputLabel.stakingType": "ステーキングタイプ",
  "inputLabel.status": "スターテス",
  "inputLabel.timeline": "Time line",
  "inputLabel.to": "宛先",
  "inputLabel.tokenType": "トークンタイプ",
  "inputLabel.totalBonded": "トータルボンド",
  "inputLabel.totalMembers": "トータルメンバー",
  "inputLabel.totalNominators": "総ノミネーター",
  "inputLabel.totalReward": "総報酬",
  "inputLabel.totalStake": "トータルステーク",
  "inputLabel.totalStaked": "ステーク総額",
  "inputLabel.totalSupply": "Total supply",
  "inputLabel.totalWinner": "Total winner",
  "inputLabel.transactionStatus": "トランザクションステータス",
  "inputLabel.transactionTime": "トランザクション時間",
  "inputLabel.transactionType": "トランザクションタイプ",
  "inputLabel.type": "タイプ",
  "inputLabel.unclaimedRewards": "未請求の報酬",
  "inputLabel.unstakeAmount": "アンステーキング額",
  "inputLabel.unstakeAmountCancelled": "キャンセルされたアンステーク額",
  "inputLabel.unstaked": "アンステークされています",
  "inputLabel.unstakeFromAcc": "アカウントからのアンステーク",
  "inputLabel.unstakingPeriod": "ステーキング期間",
  "inputLabel.validator": "バリデーター",
  "inputLabel.validators": "バリデーター",
  "inputLabel.waiting": "待っている",
  "inputLabel.withdrawalAmount": "引き出し額",
  "inputLabel.withdrawalReady": "引き出し準備完了",
  "inputLabel.withdrawFromAcc": "アカウントから引き出す",
  "inputLabel.withdrawInADay": "1日以内に引き出す",
  "inputLabel.withdrawInXDays": "{0}に引き出す",
  "message.applyDoneMessage": "すべてのアカウントのマスターパスワードが更新されました。",
  "message.applyDoneTitle": "あなたはすべて完了です！",
  "message.apy": "- APY：",
  "message.bonded": "ボンドされた数：",
  "message.buyMessage": "このトランザクションを完了するために、選択したサプライヤーに移動します",
  "message.cannotGetBalance": "残高を取得できません",
  "message.changeMasterPasswordMessage1": "新しいパスワード作成をするには、現在のパスワードを入力する必要があります。",
  "message.changeMasterPasswordMessage2": "このパスワードを使用して、アカウントのロックを解除",
  "message.claimRewardMessage1": "あなたの報酬は請求後、プールに戻されます。",
  "message.claimRewardMessage2": "あなたの報酬は請求後、移行可能な残高に加算されます。",
  "message.commission": "コミッション：{0}％",
  "message.connectedAccounts": "{0}  のアカウントが接続",
  "message.connectedNetworkConnected": "{0} のネットワークが接続",
  "message.connectedNetworks": "{0} ネットワーク",
  "message.connectSuccessfully": "Connection successful",
  "message.connectWalletConnectMessage": "「接続」をクリックすると、このdAppがあなたの公開アドレスを見ることを許可します。",
  "message.deleteNetworkMessage": "このネットワークを削除しようとしています",
  "message.deleteNftMessage": "このNFTコレクションを削除しようとしています",
  "message.deleteTokenMessage": "このトークンを削除しようとしています",
  "message.disconnectModalMessage": "接続を切断すると、SubWalletとdApp上でこの接続は表示されなくなります。",
  "message.enableTokenOnChain": "{0} 上で{1}を有効にしてください",
  "message.failToDisconnect": "切断に失敗",
  "message.forgotPasswordMessage": "パスワードはお預かりいたしません。パスワードをお忘れの場合は、シークレットリカバリーフレーズを使ってウォレットをリセットする必要があります",
  "message.generalTermWarning": "「私は、SubWallet とそのすべての機能の使用を規定する本契約の条件を理解し、これに同意します」ボックスにチェックを入れて続行してください",
  "message.masterPasswordWarning": "「SubWallet ではこのパスワードを回復できないことを理解しています」ボックスにチェックを入れて続行してください",
  "message.migrateMasterPasswordForBiometric": "For easier password management, master password will be applied in place of PIN code in previous versions. To keep using biometric authentication, please enter your master password and verify your biometric again",
  "message.networkSupported": "{0} のネットワークをサポート",
  "message.noticeForNewLoginMethod": "For easier password management, master password will be applied in place of PIN code in previous versions. You need to enter your master password to unlock SubWallet",
  "message.poolId": "プール#{0}",
  "message.requestCreateMasterPassword": "マスターパスワードは、複数のアカウントにアクセスするためのパスワードです。マスターパスワードが確認されると、お取引のたびにパスワードを手入力する必要がなくなります",
  "message.selectedXValidator": "選択された{0} バリデーター",
  "message.supportedNetworks": "サポートネットワーク",
  "message.transactionDoneMessage": "あなたのリクエストは送信されました。トランザクション履歴ページでその進捗を確認できます。",
  "message.unableToFetchInformation": "Unable to fetch {0} information",
  "message.unBondMessage": "アンボンドされると、あなたの資金は{0}後に引き出すことができます。",
  "message.unknownNetworks": "{0} の不明なネットワーク",
  "message.xcmTransferWarningMessage": "You'll need to pay an additional fee for the destination network in a cross-chain transfer. This fee cannot be calculated in advance.",
  "message.xcmTransferWarningTitle": "Pay attention!",
  "nftScreen.nftDetail.createdBy": "によって作成された",
  "nftScreen.nftDetail.properties": "プロパティ",
  "nftScreen.nftDetail.rarity": "レアリティ",
  "nftScreen.nftDetail.resourcesOrInventory": "リソースまたはインベントリ",
  "notificationMessage.addProviderSuccessfully": "プロバイダーを正常に追加しました",
  "notificationMessage.addTokenSuccessfully": "トークンを正常に追加しました",
  "notificationMessage.comingSoon": "近日公開",
  "notificationMessage.deleteChainSuccessfully": "チェーンを正常に削除しました",
  "notificationMessage.deleteNftCollectionSuccessfully": "NFTコレクションを正常に削除しました",
  "notificationMessage.deleteNftCollectionUnsuccessfully": "NFTコレクションの削除に失敗しました",
  "notificationMessage.importedChainSuccessfully": "チェーンを正常にインポートしました",
  "notificationMessage.pleaseTryAgain": "エラーが発生しました。もう一度やり直してください",
  "notificationMessage.updatedChainSuccessfully": "チェーンを正常に更新しました",
  "notificationMessage.warningNeverRequirePassword": "Choosing this option can affect your wallet security",
  "notificationMessage.watchOnlyNoti": "使用しているアカウントはウォッチ専用です。資産を送信することはできません",
  "notifyUnstable.buttonCancel": "Remind me later",
  "notifyUnstable.buttonRead": "Learn how to back up",
  "notifyUnstable.buttonReject": "Don't show again",
  "notifyUnstable.message": "Due to the instability of iOS 17, we highly recommend that you back up your seed phrase and reinstall SubWallet for better performance",
  "notifyUnstable.title": "Back up your seed phrase",
  "placeholder.accountAddress": "アカウントアドレス",
  "placeholder.accountName": "アカウント名",
  "placeholder.amount": "額",
  "placeholder.blockExplorer": "ブロックエクスプローラー",
  "placeholder.campaignName": "Campaign name",
  "placeholder.confirmPassword": "パスワードを確認",
  "placeholder.connectWalletPlaceholder": "URIを入力または貼り付けてください。",
  "placeholder.crowdloanUrl": "クラウドローンURL",
  "placeholder.currentPassword": "現在のパスワード",
  "placeholder.decimals": "小数",
  "placeholder.destinationNetwork": "宛先ネットワーク",
  "placeholder.enterOrPasteAnAddress": "アドレスを入力または貼り付けます",
  "placeholder.enterOrPastePrivateKey": "秘密鍵を入力または貼り付けます",
  "placeholder.enterPassword": "パスワードを入力",
  "placeholder.enterPrivateKey": "秘密鍵を入力",
  "placeholder.estimatedFee": "推定料金",
  "placeholder.networkName": "ネットワーク名",
  "placeholder.networkType": "ネットワークタイプ",
  "placeholder.password": "パスワード",
  "placeholder.priceId": "プライス ID",
  "placeholder.providerUrl": "プロバイダーURL",
  "placeholder.searchAddressBook": "アカウント名",
  "placeholder.searchCollectionName": "コレクション名を検索",
  "placeholder.searchHistory": "検索履歴",
  "placeholder.searchNetwork": "ネットワークを検索",
  "placeholder.searchNftNameOrId": "NFT名またはIDを検索",
  "placeholder.searchOrEnterWebsite": "Webサイトを検索",
  "placeholder.searchPool": "プールを検索",
  "placeholder.searchProject": "検索をプロジェクト",
  "placeholder.searchToken": "トークンを検索",
  "placeholder.searchValidator": "バリデーターを検索",
  "placeholder.searchWebsite": "検索またはWebサイトを入力",
  "placeholder.secretPhrase": "シークレットフレーズ",
  "placeholder.seedPhrase": "シードフレーズ",
  "placeholder.selectAccount": "アカウントを選択",
  "placeholder.selectChain": "チェーンを選択",
  "placeholder.selectCollator": "コレーターを選択",
  "placeholder.selectNetwork": "ネットワークを選択",
  "placeholder.selectNftType": "NFTタイプを選択",
  "placeholder.selectPool": "プールを選択",
  "placeholder.selectRequest": "リクエストを選択",
  "placeholder.selectService": "サービスを選択",
  "placeholder.selectSupplier": "サプライヤーを選択",
  "placeholder.selectToken": "トークンを選択",
  "placeholder.selectTokenType": "トークンタイプを選択",
  "placeholder.selectValidator": "バリデーターを選択",
  "placeholder.senderNetwork": "送信者ネットワーク",
  "placeholder.symbol": "シンボル",
  "placeholder.typeOrPasteContractAddress": "コントラクトアドレスを入力または貼り付けてください",
  "placeholder.typeYourSubwalletPassword": "SubWallet パスワードを入力",
  "placeholder.unstakingAmount": "アンステーキングしている額",
  "removeAccount.removeAccountMessage": "このアプリケーションからこのアカウントにアクセスできなくなります",
  "removeAccount.removeAccountTitle": "このアカウントを削除",
  "sendToken.senderAvailableBalance": "送信可能残高",
  "sendToken.sendTokenMessage": "次の詳細でトークンを転送",
  "settings.aboutSubwallet": "SubWallet について",
  "settings.alwaysRequire": "Always",
  "settings.appLock": "アプリロック",
  "settings.changePassword": "パスワードを変更",
  "settings.changeYourPinCode": "PINコードを変更",
  "settings.communityAndSupport": "コミュニティとサポート",
  "settings.discord": "ディスコード",
  "settings.faceId": "Face ID / Touch ID",
  "settings.generalSettings": "一般設定",
  "settings.ifLeftFor10Minutes": "10分間放置した場合",
  "settings.ifLeftFor15Minutes": "15分間放置した場合",
  "settings.ifLeftFor15Seconds": "15秒間放置した場合",
  "settings.ifLeftFor1Hour": "1時間放置した場合",
  "settings.ifLeftFor1Minute": "1分間放置した場合",
  "settings.ifLeftFor30Minutes": "30分間放置した場合",
  "settings.ifLeftFor30Seconds": "30秒間放置した場合",
  "settings.ifLeftFor5Minutes": "5分間放置した場合",
  "settings.immediately": "すぐに",
  "settings.language": "言語",
  "settings.lock": "ロック",
  "settings.manageAddressBook": "アドレス帳を管理",
  "settings.manageNetworks": "ネットワークを管理",
  "settings.manageTokens": "トークンを管理",
  "settings.manageWalletConnectDapp": "WalletConnect dAppを管理",
  "settings.manageWebsiteAccess": "ウェブサイトへのアクセスを管理",
  "settings.networksAndTokens": "ネットワークとトークン",
  "settings.neverRequire": "Never",
  "settings.notifications": "通知",
  "settings.pinCode": "PIN コード",
  "settings.privacyPolicy": "プライバシーポリシー",
  "settings.securitySettings": "セキュリティ設定",
  "settings.telegram": "テレグラム",
  "settings.termOfService": "利用規約",
  "settings.termOfUse": "Terms of use",
  "settings.termsOfService": "利用規約",
  "settings.tokens": "トークン",
  "settings.twitter": "ツイッター",
  "settings.userGuide": "ユーザーガイド",
  "settings.walletTheme": "ウォレットのテーマ",
  "settings.website": "Webサイト",
  "settings.webViewDebugger": "Webビューデバッガー",
  "settings.whenCloseApp": "アプリを閉じるとき",
  "signingAction.approveRequestThisAcc": "このアカウントのリクエストを承認しますか？",
  "signingAction.basic": "基本",
  "signingAction.data": "データ",
  "signingAction.detail": "詳細",
  "signingAction.era": "時代",
  "signingAction.gas": "ガス",
  "signingAction.gasPrice": "ガス価格",
  "signingAction.message": "メッセージ",
  "signingAction.method": "方法",
  "signingAction.nonce": "ノンス",
  "signingAction.period": "期間",
  "signingAction.phase": "段階",
  "signingAction.signature": "サイン",
  "signingAction.tip": "ヒント",
  "signingAction.to": "宛先",
  "signingAction.value": "額",
  "stakingScreen.afterInflation": "インフレ後",
  "stakingScreen.balanceList.stakingAppearHere": "あなたのステーキングアカウントがここに表示されます",
  "stakingScreen.bonded": "ボンド",
  "stakingScreen.earningReward": "報酬の獲得",
  "stakingScreen.highestBonded": "最大総ボンド数",
  "stakingScreen.highestReturn": "最高の年間収益",
  "stakingScreen.lowestActiveStake": "最小アクティブステーク",
  "stakingScreen.lowestCommission": "最低コミッション",
  "stakingScreen.lowestMember": "最小総メンバー数",
  "stakingScreen.maximumSelectableValidators": "選択できるバリデータは {0} だけです。",
  "stakingScreen.nomination": "Nomination",
  "stakingScreen.notEarning": "獲得なし",
  "stakingScreen.selectedCollator": "選択されたコレーター",
  "stakingScreen.selectedPool": "選択されたプール",
  "stakingScreen.selectUnstakeRequest": "アンステークリクエストを選択",
  "tabName.browser": "ブラウザー",
  "tabName.crowdloans": "クラウドローン",
  "tabName.earning": "Earning",
  "tabName.nfts": "NFTs",
  "tabName.staking": "ステーキング",
  "tabName.tokens": "トークン",
  "title.addProvider": "プロバイダーを追加",
  "title.approveRequest": "リクエストを承認",
  "title.authorizeMessage": "メッセージを承認",
  "title.authorizeRequestTitle": "リクエストを承認",
  "title.authorizeTransaction": "トランザクションの承認",
  "title.chain": "チェーン",
  "title.chainSelect": "チェーンの選択",
  "title.earning": "Earning",
  "title.exportAccount": "エクスポートアカウント",
  "title.exportQrSigner": "QR署名者をエクスポート",
  "title.filters": "フィルター",
  "title.history": "ヒストリー",
  "title.importNft": "NFTをインポート",
  "title.login": "ログイン",
  "title.metadataTitlePart1": "このアップデートを承認すると、メタデータが同期されます",
  "title.metadataTitlePart2": "chain from",
  "title.moreOptions": "その他のオプション",
  "title.network": "ネットワーク",
  "title.networks": "ネットワーク",
  "title.nftDetail": "NFTの詳細",
  "title.nftList": "NFTのリスト",
  "title.phishingDetected": "フィッシングが検出されました",
  "title.qrScanner": "QRスキャナー",
  "title.scanPayload": "QRをスキャン",
  "title.scanQrCode": "QRコードをスキャン",
  "title.scanQrCodeSubTitle": "Scan QR code to send or connect to DApp",
  "title.selectUnit": "ユニットを選択",
  "title.sendTransaction": "トランザクションを送信",
  "title.serviceSelect": "サービスを選択",
  "title.signMessage": "署名メッセージ",
  "title.signTransaction": "トランザクションに署名",
  "title.slogan": "Polkadot, Substrate & Ethereum wallet",
  "title.staking": "ステーキング",
  "title.stakingDetail": "ステーキングの詳細",
  "title.stakingNetwork": "ネットワークを選択",
  "title.tickTheCheckbox": "読み取りの確認",
  "title.token": "トークン",
  "title.validators": "バリデーターを選択",
  "tokenDetail.locked": "ロックされています",
  "tokenDetail.transferable": "転送可能",
  "transferNft.send": "送信",
  "warningMessage.balanceTooLow": "手数料をまかなうには残高が少なすぎます",
  "warningMessage.clearHistoryWarningMessage": "すべての履歴を消去することを確認してください",
  "warningMessage.doNotMatchPasswordWarning": "パスワードが一致していません",
  "warningMessage.enableNetworkMessage": "選択したネットワークが有効になっていません。このボタンをクリックして有効にするか、他のネットワークを選択してください",
  "warningMessage.ethSignWarningMessage": "このメッセージへの署名は危険です。この署名は、あなたのアカウントとそのすべての資産の完全な制御を要求元のサイトに許可するなど、あなたのアカウントに代わってあらゆる操作を実行する可能性があります。このメッセージに署名するのは、自分が何をしているかをわかっているか、要求元サイトを完全に信頼している場合のみにしてください",
  "warningMessage.expiredConnectionMessage": "接続の有効期限が切れました。dAppから新しい接続を作成してください。",
  "warningMessage.featureIsNotAvailable": "この機能は、選択したアカウントでは使用できません",
  "warningMessage.initSecretPhrase": "リカバリーフレーズは安全な場所に保管し、決して公開しないでください。このフレーズを持っていれば、誰でもあなたの資産をコントロールすることができます",
  "warningMessage.insufficientBalanceMessage": "Your available balance is {0} {1}, you need to leave {2} {1} as minimal balance (existential deposit) and pay network fees. Make sure you have at least {3} {1} in your transferable balance to proceed.",
  "warningMessage.invalidJsonFile": "無効なJSONファイル",
  "warningMessage.invalidQRCode": "無効なQRコード",
  "warningMessage.isNotSameAddressAndTokenType": "このタイプのアカウントとトークンの転送はサポートされていません",
  "warningMessage.networkUnSupportQrSigner": "このネットワークは、QR-Signerアカウントでこの機能をサポートしていません",
  "warningMessage.noEvmAccountMessage": "EVMアカウントはありません。続行するためにアカウントを作成、インポート、または復元してくださ",
  "warningMessage.noInternetMessage": "インターネットに接続できません。後でもう一度お試しください。",
  "warningMessage.noNetworkAvailable": "利用可能なネットワークはありません",
  "warningMessage.noServiceAvailable": "利用可能なサービスはありません",
  "warningMessage.noSubstrateAccountMessage": "あなたはSubstrateアカウントも持っていません。続行するには、アカウントを作成、インポート、または復元してください",
  "warningMessage.passwordTooShort": "パスワードが短すぎます",
  "warningMessage.phishingMessage": "このサイトがブロックされているのは、SubWalletアプリがこのウェブサイトによってアカウントとトークンのセキュリティが脅かされる可能性があると判断したためです",
  "warningMessage.readOnly": "ウォッチのみのアカウントを使用しています",
  "warningMessage.requireMessage": "この項目は必須です",
  "warningMessage.secretPhraseWarning": "リカバリーフレーズを紛失した場合、取り戻す方法はありません。必ず自分だけがアクセスできる安全な場所に保管してください",
  "warningMessage.thresholdLagerThan": "ステーク額は閾値はより大きくなければなりません",
  "warningMessage.tokenExists": "そのトークンはすでに存在しています。",
  "warningMessage.trustSiteMessage": "接続する前にこのサイトを信頼していることを確認してください",
  "warningMessage.unableDecode": "指定されたパスフレーズを使用してもデコードできません",
  "warningMessage.unsupportedNetworkMessage": "少なくとも選択された1つのネットワークが利用できない",
  "warningMessage.unSupportSigning": "この機能は、選択したアカウントでは使用できません",
  "warningMessage.webRunnerDeadMessage": "問題が発生しました。後でもう一度お試しいただくか、アプリケーションを再起動してください。",
  "warningTitle.clearHistory": "履歴をクリア",
  "warningTitle.error": "エラー！",
  "warningTitle.expiredConnectionTitle": "接続期限切れ",
  "warningTitle.insufficientBalance": "Insufficient balance",
  "warningTitle.unsupportedNetworkTitle": "サポートされていないネットワーク",
  "warningTitle.updateNetwork": "ネットワークを更新",
  "warningTitle.warning": "警告",
  "warningTitle.whatIfLoseRecoveryPhrase": "リカバリーフレーズを紛失した場合はどうなりますか？",
  "warning.warningAccMessage": "あなたのキーを持っている人は誰でもあなたのアカウントにある資産を使用できます",
  "warning.warningAccTitle": "警告：この鍵を開示しないでください",
  "warning.warningCreatePasswordTitle": "常に強力なパスワードを選択してください！",
  "warning.warningPasswordMessage": "最低6文字。大文字、数字、特殊文字を推奨します。",
  "warning.warningPasswordTitle": "常に強力なパスワードを選択してください！",
  "welcomeScreen.attachAccLabel": "アカウントをアタッチ",
  "welcomeScreen.attachAccMessage": "秘密鍵なしでアカウントをアタッチ",
  "welcomeScreen.createAccLabel": "新しいアカウントを作成",
  "welcomeScreen.createAccMessage": "SubWalletで新しいアカウントを作成",
  "welcomeScreen.forgetAccount": "アカウントをお忘れですか？",
  "welcomeScreen.importAccLabel": "アカウントをインポート",
  "welcomeScreen.importAccMessage": "既存のアカウントをインポート",
  "welcomeScreen.welcomeBackMessage": "パスワードを入力して、ウォレットのロックを解除",
  "welcomeScreen.welcomeBackTitle": "お帰りなさい！",
  "welcomeScreen.welcomeMessage": ""
}